ugbio_comparison/__init__.py
ugbio_comparison/comparison_pipeline.py
ugbio_comparison/comparison_utils.py
ugbio_comparison/run_comparison_pipeline.py
ugbio_comparison/sv_comparison_pipeline.py
ugbio_comparison/vcf_comparison_utils.py
ugbio_comparison-1.20.0.dist-info/METADATA
ugbio_comparison-1.20.0.dist-info/WHEEL
ugbio_comparison-1.20.0.dist-info/entry_points.txt
ugbio_comparison-1.20.0.dist-info/top_level.txt
ugbio_comparison-1.20.0.dist-info/RECORD
